{"data_mtime":1707388583,"dep_lines":[1,1,1,2,3,4],"dep_prios":[5,30,30,5,5,5],"dependencies":["builtins","abc","typing"],"hash":"f4c705cc1e3b377e78a9c9125fc4312fb46b903fc3dc344fc9d73fe62bec56a5","id":"articles.models","ignore_all":true,"interface_hash":"fee322a65b68cb41228bb259d1093e6ec87ca56c606784c7b5d04e9385914fe2","mtime":1707388403,"options":{"allow_redefinition":false,"allow_untyped_globals":false,"always_false":[],"always_true":[],"bazel":false,"check_untyped_defs":false,"disable_bytearray_promotion":false,"disable_error_code":[],"disable_memoryview_promotion":false,"disabled_error_codes":[],"disallow_any_decorated":false,"disallow_any_explicit":false,"disallow_any_expr":false,"disallow_any_generics":false,"disallow_any_unimported":false,"disallow_incomplete_defs":false,"disallow_subclassing_any":false,"disallow_untyped_calls":false,"disallow_untyped_decorators":false,"disallow_untyped_defs":false,"enable_error_code":[],"enabled_error_codes":[],"extra_checks":false,"follow_imports":"normal","follow_imports_for_stubs":false,"ignore_errors":false,"ignore_missing_imports":false,"implicit_optional":false,"implicit_reexport":true,"local_partial_types":false,"mypyc":false,"new_type_inference":false,"platform":"linux","plugins":[],"strict_concatenate":false,"strict_equality":false,"strict_optional":true,"warn_no_return":true,"warn_return_any":false,"warn_unreachable":false,"warn_unused_ignores":false},"path":"/home/natalie/projects/news/articles/models.py","plugin_data":null,"size":602,"suppressed":["django.conf","django.db","django.urls"],"version_id":"1.6.1"}